<?xml version="1.0" encoding="utf-8"?>
<Roots >
  <Roots.Interfaces>
    <RootInterface FullName="Windows.UI.Xaml.Data.IValueConverter" />
  </Roots.Interfaces>
  <Roots.PropertyPathNames>
    <RootPropertyPathName Name="Item" />
    <RootPropertyPathName Name="Country" />
    <RootPropertyPathName Name="LabelContent" />
    <RootPropertyPathName Name="Image" />
    <RootPropertyPathName Name="Description" />
    <RootPropertyPathName Name="Title" />
    <RootPropertyPathName Name="Subtitle" />
    <RootPropertyPathName Name="SalesVsTarget" />
    <RootPropertyPathName Name="RangeStart" />
    <RootPropertyPathName Name="RangeEnd" />
    <RootPropertyPathName Name="IndicatorList" />
    <RootPropertyPathName Name="YValues" />
    <RootPropertyPathName Name="LabelYValues" />
    <RootPropertyPathName Name="SelectedData" />
    <RootPropertyPathName Name="Stocks" />
    <RootPropertyPathName Name="Color1" />
    <RootPropertyPathName Name="CurrentLow" />
    <RootPropertyPathName Name="CurrentHigh" />
    <RootPropertyPathName Name="PreviousClose" />
    <RootPropertyPathName Name="Color" />
    <RootPropertyPathName Name="StockName" />
    <RootPropertyPathName Name="Visibility" />
    <RootPropertyPathName Name="SelectedIndex" />
    <RootPropertyPathName Name="ChartVisibility" />
    <RootPropertyPathName Name="Datas" />
    <RootPropertyPathName Name="SelectedStock" />
    <RootPropertyPathName Name="RectX" />
    <RootPropertyPathName Name="RectY" />
    <RootPropertyPathName Name="Width" />
    <RootPropertyPathName Name="Height" />
    <RootPropertyPathName Name="ZoomFactor" />
    <RootPropertyPathName Name="ZoomPosition" />
    <RootPropertyPathName Name="Datalist" />
    <RootPropertyPathName Name="power" />
    <RootPropertyPathName Name="Score" />
    <RootPropertyPathName Name="PlayerName" />
    <RootPropertyPathName Name="DataModel" />
    <RootPropertyPathName Name="labelTemplate" />
    <RootPropertyPathName Name="YData" />
    <RootPropertyPathName Name="Category" />
    <RootPropertyPathName Name="Products" />
    <RootPropertyPathName Name="BoxWhiskerData" />
    <RootPropertyPathName Name="RevenueDetails" />
    <RootPropertyPathName Name="Product" />
    <RootPropertyPathName Name="DataPoints" />
    <RootPropertyPathName Name="AdornmentsInfo" />
    <RootPropertyPathName Name="AdornmentInfo4" />
    <RootPropertyPathName Name="AdornmentInfo7" />
    <RootPropertyPathName Name="AdornmentInfo6" />
    <RootPropertyPathName Name="AdornmentInfo3" />
    <RootPropertyPathName Name="AdornmentInfo2" />
    <RootPropertyPathName Name="AdornmentInfo1" />
    <RootPropertyPathName Name="AdornmentInfo5" />
    <RootPropertyPathName Name="SplineRangeAreaAdornmentInfo" />
    <RootPropertyPathName Name="stocks" />
    <RootPropertyPathName Name="PlantDetails" />
    <RootPropertyPathName Name="CurrencyDetails" />
    <RootPropertyPathName Name="AdornmentInfo" />
    <RootPropertyPathName Name="Interior" />
    <RootPropertyPathName Name="X1" />
    <RootPropertyPathName Name="X2" />
    <RootPropertyPathName Name="Y1" />
    <RootPropertyPathName Name="Y2" />
    <RootPropertyPathName Name="ScatterHeight" />
    <RootPropertyPathName Name="ScatterWidth" />
    <RootPropertyPathName Name="Data" />
    <RootPropertyPathName Name="cai" />
    <RootPropertyPathName Name="EnergyProductions" />
    <RootPropertyPathName Name="Stroke" />
    <RootPropertyPathName Name="VerticalErrorValue" />
    <RootPropertyPathName Name="HorizontalErrorValue" />
    <RootPropertyPathName Name="BorderBrush" />
    <RootPropertyPathName Name="Foreground" />
    <RootPropertyPathName Name="Low" />
    <RootPropertyPathName Name="High" />
    <RootPropertyPathName Name="Y" />
    <RootPropertyPathName Name="Y3" />
    <RootPropertyPathName Name="MedalDetails" />
    <RootPropertyPathName Name="TestingModel" />
    <RootPropertyPathName Name="LineData" />
    <RootPropertyPathName Name="List" />
    <RootPropertyPathName Name="RangeData" />
    <RootPropertyPathName Name="DataCollection" />
    <RootPropertyPathName Name="HiloViewModel" />
    <RootPropertyPathName Name="StockPriceDetails" />
    <RootPropertyPathName Name="ViewRangeStart" />
    <RootPropertyPathName Name="Collection" />
    <RootPropertyPathName Name="Label" />
    <RootPropertyPathName Name="IsSeriesVisible" />
    <RootPropertyPathName Name="Value" />
    <RootPropertyPathName Name="FacebookStatistics" />
    <RootPropertyPathName Name="ActiveUsers" />
    <RootPropertyPathName Name="RegisteredUsers" />
    <RootPropertyPathName Name="PaletteList" />
    <RootPropertyPathName Name="Users" />
    <RootPropertyPathName Name="CompanyDetails" />
    <RootPropertyPathName Name="AdornmentInfo11" />
    <RootPropertyPathName Name="AdornmentInfo10" />
    <RootPropertyPathName Name="AdornmentInfo9" />
    <RootPropertyPathName Name="Metric" />
    <RootPropertyPathName Name="Population" />
    <RootPropertyPathName Name="AdornmentInfo8" />
    <RootPropertyPathName Name="CountryDetails" />
    <RootPropertyPathName Name="SelectedItemsPercentage" />
    <RootPropertyPathName Name="SelectedItemName" />
    <RootPropertyPathName Name="XValue" />
    <RootPropertyPathName Name="YValue" />
    <RootPropertyPathName Name="Text" />
    <RootPropertyPathName Name="SelectedItem" />
    <RootPropertyPathName Name="Brush" />
    <RootPropertyPathName Name="ScalebreakDatas" />
    <RootPropertyPathName Name="Data2" />
    <RootPropertyPathName Name="SelectedValue" />
    <RootPropertyPathName Name="Data1" />
    <RootPropertyPathName Name="SalesCollection" />
    <RootPropertyPathName Name="SelectionStyles" />
    <RootPropertyPathName Name="SelectionModes" />
    <RootPropertyPathName Name="ColumnChartViewModel" />
    <RootPropertyPathName Name="AdornmentInfo520" />
    <RootPropertyPathName Name="AdornmentInfo510" />
    <RootPropertyPathName Name="AdornmentInfo50" />
    <RootPropertyPathName Name="AdornmentInfo52" />
    <RootPropertyPathName Name="AdornmentInfo51" />
    <RootPropertyPathName Name="AreaChartViewModel" />
    <RootPropertyPathName Name="AdornmentInfo13" />
    <RootPropertyPathName Name="TemperatureData" />
    <RootPropertyPathName Name="AdornmentInfo12" />
    <RootPropertyPathName Name="BarChartViewModel" />
    <RootPropertyPathName Name="GoldInventoryDetails" />
    <RootPropertyPathName Name="AdornmentInfo120" />
    <RootPropertyPathName Name="AdornmentInfo110" />
    <RootPropertyPathName Name="Margin" />
    <RootPropertyPathName Name="Summer" />
    <RootPropertyPathName Name="Spring" />
    <RootPropertyPathName Name="Autumn" />
    <RootPropertyPathName Name="LineChartViewModel" />
    <RootPropertyPathName Name="MonthlyExpense" />
    <RootPropertyPathName Name="AnnualDetails" />
    <RootPropertyPathName Name="AdronmentInfo4" />
    <RootPropertyPathName Name="AdronmentInfo3" />
    <RootPropertyPathName Name="AdronmentInfo2" />
    <RootPropertyPathName Name="AdronmentInfo1" />
    <RootPropertyPathName Name="ClimateData" />
    <RootPropertyPathName Name="Rank" />
    <RootPropertyPathName Name="CompanyName" />
    <RootPropertyPathName Name="Imagepath" />
    <RootPropertyPathName Name="CommodityDetails" />
    <RootPropertyPathName Name="NewValue" />
    <RootPropertyPathName Name="SalesData" />
    <RootPropertyPathName Name="SneakersDetail" />
    <RootPropertyPathName Name="LoadDetails" />
  </Roots.PropertyPathNames>
  <Roots.RootTypes>
    <RootType FullName="Windows.UI.Xaml.Application">
      <RootProperty Name="RequestedTheme" />
    </RootType>
    <RootType FullName="Windows.UI.Xaml.Controls.UserControl">
      <RootProperty Name="Content" />
      <RootProperty Name="RequestedTheme" />
    </RootType>
    <RootType FullName="Windows.UI.Xaml.Controls.Grid">
      <RootProperty Name="Children" />
      <RootProperty Name="Resources" />
      <RootProperty Name="Background" />
      <RootProperty Name="ColumnDefinitions" />
      <RootProperty Name="Margin" />
      <RootProperty Name="Width" />
      <RootProperty Name="Height" />
      <RootProperty Name="HorizontalAlignment" />
      <RootProperty Name="ChildrenTransitions" />
      <RootProperty Name="DataContext" />
      <RootProperty Name="RowDefinitions" />
      <RootProperty Name="Name" />
      <RootProperty Name="VerticalAlignment" />
      <RootProperty Name="IsHitTestVisible" />
      <RootMethod Name="GetColumn" />
      <RootMethod Name="SetColumn" />
      <RootMethod Name="GetRow" />
      <RootMethod Name="SetRow" />
      <RootMethod Name="GetColumnSpan" />
      <RootMethod Name="SetColumnSpan" />
      <RootMethod Name="GetRowSpan" />
      <RootMethod Name="SetRowSpan" />
    </RootType>
    <RootType FullName="Windows.UI.Xaml.ResourceDictionary" />
    <RootType FullName="Syncfusion.UI.Xaml.Charts.ChartColorModel">
      <RootProperty Name="CustomBrushes" />
    </RootType>
    <RootType FullName="Syncfusion.SampleBrowser.UWP.SfChart.DataConverter" />
    <RootType FullName="Windows.UI.Xaml.DataTemplate">
      <RootProperty Name="Template" />
    </RootType>
    <RootType FullName="Windows.UI.Xaml.Shapes.Line">
      <RootProperty Name="Stroke" />
      <RootProperty Name="X1" />
      <RootProperty Name="X2" />
      <RootProperty Name="Y1" />
      <RootProperty Name="Y2" />
      <RootProperty Name="StrokeEndLineCap" />
      <RootProperty Name="StrokeThickness" />
      <RootProperty Name="StrokeDashArray" />
    </RootType>
    <RootType FullName="Windows.UI.Xaml.Shapes.Shape">
      <RootProperty Name="Stroke" />
      <RootProperty Name="StrokeThickness" />
      <RootProperty Name="Fill" />
    </RootType>
    <RootType FullName="Syncfusion.SampleBrowser.UWP.SfChart.ColorConverter" />
    <RootType FullName="Windows.UI.Xaml.Shapes.Path">
      <RootProperty Name="RenderTransformOrigin" />
      <RootProperty Name="Data" />
      <RootProperty Name="Stretch" />
      <RootProperty Name="Fill" />
      <RootProperty Name="Width" />
      <RootProperty Name="Height" />
      <RootProperty Name="RenderTransform" />
      <RootProperty Name="Margin" />
      <RootProperty Name="Stroke" />
      <RootProperty Name="StrokeEndLineCap" />
      <RootProperty Name="StrokeThickness" />
    </RootType>
    <RootType FullName="Windows.UI.Xaml.Setter">
      <RootProperty Name="Property" />
      <RootProperty Name="Value" />
    </RootType>
    <RootType FullName="Windows.UI.Xaml.Shapes.Rectangle">
      <RootProperty Name="Fill" />
      <RootProperty Name="IsHitTestVisible" />
      <RootProperty Name="Stroke" />
      <RootProperty Name="StrokeEndLineCap" />
      <RootProperty Name="StrokeDashArray" />
      <RootProperty Name="Opacity" />
      <RootProperty Name="StrokeDashOffset" />
      <RootProperty Name="Height" />
      <RootProperty Name="StrokeThickness" />
      <RootProperty Name="Width" />
      <RootProperty Name="Tag" />
      <RootProperty Name="Margin" />
      <RootProperty Name="VerticalAlignment" />
      <RootProperty Name="RadiusY" />
      <RootProperty Name="RadiusX" />
      <RootProperty Name="HorizontalAlignment" />
    </RootType>
    <RootType FullName="Windows.UI.Xaml.Controls.TextBlock">
      <RootProperty Name="Padding" />
      <RootProperty Name="Text" />
      <RootProperty Name="FontSize" />
      <RootProperty Name="HorizontalAlignment" />
      <RootProperty Name="VerticalAlignment" />
      <RootProperty Name="FontWeight" />
      <RootProperty Name="Foreground" />
      <RootProperty Name="FontFamily" />
      <RootProperty Name="TextTrimming" />
      <RootProperty Name="TextWrapping" />
      <RootProperty Name="LineHeight" />
      <RootProperty Name="LineStackingStrategy" />
      <RootProperty Name="Style" />
      <RootProperty Name="MaxHeight" />
      <RootProperty Name="Height" />
      <RootProperty Name="Margin" />
      <RootProperty Name="Opacity" />
      <RootProperty Name="TextAlignment" />
      <RootProperty Name="Width" />
      <RootProperty Name="Inlines" />
      <RootProperty Name="Name" />
      <RootProperty Name="Visibility" />
      <RootProperty Name="IsHitTestVisible" />
      <RootProperty Name="FontStretch" />
      <RootProperty Name="RenderTransformOrigin" />
      <RootProperty Name="RenderTransform" />
    </RootType>
    <RootType FullName="Windows.UI.Xaml.Data.Binding">
      <RootProperty Name="Converter" />
      <RootProperty Name="Mode" />
      <RootProperty Name="ElementName" />
      <RootProperty Name="Path" />
      <RootProperty Name="Source" />
    </RootType>
    <RootType FullName="Microsoft.Xaml.DirectUI.ProxyTypes.StaticResourceExtension" />
    <RootType FullName="Windows.UI.Xaml.Media.SolidColorBrush">
      <RootProperty Name="Color" />
    </RootType>
    <RootType FullName="Syncfusion.UI.Xaml.Charts.SfChart">
      <RootProperty Name="Name" />
      <RootProperty Name="DataContext" />
      <RootProperty Name="AreaBorderThickness" />
      <RootProperty Name="VerticalAlignment" />
      <RootProperty Name="Series" />
      <RootProperty Name="PrimaryAxis" />
      <RootProperty Name="SecondaryAxis" />
      <RootProperty Name="Behaviors" />
      <RootProperty Name="Margin" />
      <RootProperty Name="BorderBrush" />
      <RootProperty Name="Visibility" />
      <RootProperty Name="Header" />
      <RootProperty Name="RowDefinitions" />
      <RootProperty Name="Watermark" />
      <RootProperty Name="AreaBorderBrush" />
      <RootProperty Name="Resources" />
      <RootProperty Name="Palette" />
      <RootProperty Name="ColorModel" />
      <RootProperty Name="Annotations" />
      <RootProperty Name="Legend" />
      <RootProperty Name="HorizontalAlignment" />
      <RootProperty Name="Height" />
      <RootProperty Name="FontSize" />
      <RootProperty Name="Width" />
      <RootProperty Name="ColumnDefinitions" />
      <RootProperty Name="TechnicalIndicators" />
      <RootProperty Name="Background" />
      <RootEvent Name="Loaded" />
      <RootEvent Name="SelectionChanged" />
    </RootType>
    <RootType FullName="Syncfusion.UI.Xaml.Charts.PieSeries">
      <RootProperty Name="YBindingPath" />
      <RootProperty Name="XBindingPath" />
      <RootProperty Name="Palette" />
      <RootProperty Name="ColorModel" />
      <RootProperty Name="ItemsSource" />
      <RootProperty Name="ConnectorType" />
      <RootProperty Name="LabelPosition" />
      <RootProperty Name="AdornmentsInfo" />
      <RootProperty Name="StartAngle" />
      <RootProperty Name="EndAngle" />
      <RootProperty Name="PieCoefficient" />
      <RootProperty Name="EnableSmartLabels" />
      <RootProperty Name="Stroke" />
      <RootProperty Name="Label" />
      <RootProperty Name="ShowTooltip" />
      <RootProperty Name="GroupTo" />
      <RootProperty Name="GroupMode" />
    </RootType>
    <RootType FullName="Syncfusion.UI.Xaml.Charts.ChartAdornmentInfo">
      <RootProperty Name="ShowMarker" />
      <RootProperty Name="Symbol" />
      <RootProperty Name="FontSize" />
      <RootProperty Name="LabelPosition" />
      <RootProperty Name="ShowLabel" />
    </RootType>
    <RootType FullName="Syncfusion.SampleBrowser.UWP.SfChart.Chartz">
      <RootProperty Name="Margin" />
      <RootProperty Name="HorizontalAlignment" />
    </RootType>
    <RootType FullName="System.String" />
    <RootType FullName="Windows.UI.Xaml.Controls.RichTextBlock">
      <RootProperty Name="Foreground" />
      <RootProperty Name="FontSize" />
      <RootProperty Name="FontFamily" />
      <RootProperty Name="TextTrimming" />
      <RootProperty Name="TextWrapping" />
      <RootProperty Name="LineHeight" />
      <RootProperty Name="LineStackingStrategy" />
      <RootProperty Name="FontWeight" />
    </RootType>
    <RootType FullName="Windows.UI.Xaml.Documents.Typography">
      <RootMethod Name="GetStylisticSet20" />
      <RootMethod Name="SetStylisticSet20" />
      <RootMethod Name="GetDiscretionaryLigatures" />
      <RootMethod Name="SetDiscretionaryLigatures" />
      <RootMethod Name="GetCaseSensitiveForms" />
      <RootMethod Name="SetCaseSensitiveForms" />
      <RootMethod Name="GetVariants" />
      <RootMethod Name="SetVariants" />
    </RootType>
    <RootType FullName="Windows.UI.Xaml.UIElement">
      <RootProperty Name="RenderTransform" />
      <RootProperty Name="Visibility" />
    </RootType>
    <RootType FullName="Windows.UI.Xaml.Controls.Primitives.ButtonBase" />
    <RootType FullName="Windows.UI.Xaml.FrameworkElement">
      <RootProperty Name="MinWidth" />
      <RootProperty Name="MinHeight" />
      <RootProperty Name="Margin" />
      <RootProperty Name="VerticalAlignment" />
      <RootProperty Name="Width" />
      <RootProperty Name="Height" />
    </RootType>
    <RootType FullName="Windows.UI.Xaml.Controls.Control">
      <RootProperty Name="Template" />
      <RootProperty Name="Foreground" />
      <RootProperty Name="FontFamily" />
      <RootProperty Name="FontWeight" />
      <RootProperty Name="FontSize" />
      <RootProperty Name="BorderBrush" />
      <RootProperty Name="Padding" />
      <RootProperty Name="Background" />
      <RootProperty Name="HorizontalContentAlignment" />
      <RootProperty Name="VerticalContentAlignment" />
    </RootType>
    <RootType FullName="Windows.UI.Xaml.Controls.RadioButton">
      <RootProperty Name="IsChecked" />
      <RootProperty Name="Content" />
      <RootProperty Name="FontSize" />
      <RootEvent Name="Checked" />
    </RootType>
    <RootType FullName="Windows.UI.Xaml.Automation.AutomationProperties">
      <RootMethod Name="GetItemType" />
      <RootMethod Name="SetItemType" />
      <RootMethod Name="GetAutomationId" />
      <RootMethod Name="SetAutomationId" />
      <RootMethod Name="GetName" />
      <RootMethod Name="SetName" />
    </RootType>
    <RootType FullName="Windows.UI.Xaml.Controls.Button">
      <RootProperty Name="Margin" />
      <RootProperty Name="HorizontalAlignment" />
      <RootProperty Name="Content" />
      <RootEvent Name="Click" />
    </RootType>
    <RootType FullName="Windows.UI.Xaml.Controls.ScrollViewer">
      <RootProperty Name="HorizontalScrollBarVisibility" />
      <RootProperty Name="VerticalScrollBarVisibility" />
      <RootProperty Name="HorizontalScrollMode" />
      <RootProperty Name="VerticalScrollMode" />
      <RootProperty Name="ZoomMode" />
      <RootProperty Name="Name" />
      <RootProperty Name="Content" />
      <RootProperty Name="Height" />
      <RootProperty Name="Margin" />
      <RootProperty Name="HorizontalAlignment" />
      <RootMethod Name="GetVerticalScrollBarVisibility" />
      <RootMethod Name="SetVerticalScrollBarVisibility" />
    </RootType>
    <RootType FullName="Windows.UI.Xaml.Controls.Panel">
      <RootProperty Name="Background" />
      <RootProperty Name="ChildrenTransitions" />
    </RootType>
    <RootType FullName="Windows.UI.Xaml.Media.Animation.TransitionCollection" />
    <RootType FullName="Windows.UI.Xaml.Media.Animation.EntranceThemeTransition">
      <RootProperty Name="FromVerticalOffset" />
      <RootProperty Name="IsStaggeringEnabled" />
      <RootProperty Name="FromHorizontalOffset" />
    </RootType>
    <RootType FullName="Windows.UI.Xaml.Controls.ToolTipService">
      <RootMethod Name="GetPlacement" />
      <RootMethod Name="SetPlacement" />
      <RootMethod Name="GetToolTip" />
      <RootMethod Name="SetToolTip" />
    </RootType>
    <RootType FullName="Windows.UI.Xaml.Controls.Image">
      <RootProperty Name="Source" />
      <RootProperty Name="Width" />
      <RootProperty Name="Height" />
      <RootProperty Name="HorizontalAlignment" />
      <RootProperty Name="VerticalAlignment" />
      <RootProperty Name="Stretch" />
      <RootProperty Name="Margin" />
    </RootType>
    <RootType FullName="Windows.UI.Xaml.Controls.ToolTip">
      <RootProperty Name="Style" />
      <RootProperty Name="Content" />
    </RootType>
    <RootType FullName="Windows.UI.Xaml.Controls.ColumnDefinition">
      <RootProperty Name="Width" />
    </RootType>
    <RootType FullName="Windows.UI.Xaml.Controls.StackPanel">
      <RootProperty Name="Width" />
      <RootProperty Name="Margin" />
      <RootProperty Name="Children" />
      <RootProperty Name="VerticalAlignment" />
      <RootProperty Name="Background" />
      <RootProperty Name="Orientation" />
      <RootProperty Name="HorizontalAlignment" />
      <RootProperty Name="Height" />
      <RootProperty Name="Padding" />
      <RootProperty Name="DataContext" />
    </RootType>
    <RootType FullName="Windows.UI.Xaml.Controls.Border">
      <RootProperty Name="Background" />
      <RootProperty Name="Margin" />
      <RootProperty Name="Width" />
      <RootProperty Name="Height" />
      <RootProperty Name="Child" />
      <RootProperty Name="Name" />
      <RootProperty Name="Padding" />
      <RootProperty Name="HorizontalAlignment" />
      <RootProperty Name="BorderThickness" />
      <RootProperty Name="CornerRadius" />
      <RootProperty Name="Visibility" />
      <RootProperty Name="BorderBrush" />
      <RootProperty Name="Resources" />
    </RootType>
    <RootType FullName="Windows.UI.Xaml.Controls.ControlTemplate">
      <RootProperty Name="TargetType" />
      <RootProperty Name="Template" />
    </RootType>
    <RootType FullName="Windows.UI.Xaml.VisualStateManager">
      <RootMethod Name="GetVisualStateGroups" />
    </RootType>
    <RootType FullName="Windows.UI.Xaml.VisualStateGroup">
      <RootProperty Name="States" />
    </RootType>
    <RootType FullName="Windows.UI.Xaml.VisualState">
      <RootProperty Name="Storyboard" />
    </RootType>
    <RootType FullName="Windows.UI.Xaml.Media.Animation.Storyboard">
      <RootProperty Name="Children" />
      <RootMethod Name="GetTargetName" />
      <RootMethod Name="SetTargetName" />
      <RootMethod Name="GetTargetProperty" />
      <RootMethod Name="SetTargetProperty" />
    </RootType>
    <RootType FullName="Windows.UI.Xaml.Media.Animation.DoubleAnimation">
      <RootProperty Name="To" />
      <RootProperty Name="Duration" />
    </RootType>
    <RootType FullName="Windows.UI.Xaml.Media.Animation.ObjectAnimationUsingKeyFrames">
      <RootProperty Name="KeyFrames" />
    </RootType>
    <RootType FullName="Windows.UI.Xaml.Media.Animation.DiscreteObjectKeyFrame">
      <RootProperty Name="KeyTime" />
      <RootProperty Name="Value" />
    </RootType>
    <RootType FullName="Microsoft.Xaml.DirectUI.ProxyTypes.TemplateBindingExtension" />
    <RootType FullName="Windows.UI.Xaml.Controls.ContentPresenter">
      <RootProperty Name="HorizontalAlignment" />
      <RootProperty Name="Margin" />
      <RootProperty Name="VerticalAlignment" />
      <RootProperty Name="Content" />
      <RootProperty Name="ContentTemplate" />
    </RootType>
    <RootType FullName="Windows.UI.Xaml.Media.TranslateTransform">
      <RootProperty Name="X" />
      <RootProperty Name="Y" />
    </RootType>
    <RootType FullName="Windows.UI.Xaml.Controls.Canvas">
      <RootProperty Name="Children" />
      <RootMethod Name="GetZIndex" />
      <RootMethod Name="SetZIndex" />
      <RootMethod Name="GetLeft" />
      <RootMethod Name="SetLeft" />
      <RootMethod Name="GetTop" />
      <RootMethod Name="SetTop" />
    </RootType>
    <RootType FullName="Syncfusion.UI.Xaml.Charts.SfDateTimeRangeNavigator">
      <RootProperty Name="ItemsSource" />
      <RootProperty Name="XBindingPath" />
      <RootProperty Name="Minimum" />
      <RootProperty Name="Maximum" />
      <RootProperty Name="ViewRangeStart" />
      <RootProperty Name="ShowGridLines" />
      <RootProperty Name="ViewRangeEnd" />
      <RootProperty Name="HigherLevelBarStyle" />
      <RootProperty Name="LowerLevelBarStyle" />
      <RootProperty Name="Content" />
      <RootProperty Name="BorderThickness" />
      <RootProperty Name="HigherLabelStyle" />
      <RootProperty Name="HigherBarTickLineStyle" />
      <RootProperty Name="ScrollbarVisibility" />
      <RootProperty Name="BorderBrush" />
      <RootProperty Name="Intervals" />
    </RootType>
    <RootType FullName="Syncfusion.UI.Xaml.Charts.LabelBarStyle">
      <RootProperty Name="Background" />
      <RootProperty Name="LabelHorizontalAlignment" />
      <RootProperty Name="SelectedLabelBrush" />
      <RootProperty Name="Position" />
    </RootType>
    <RootType FullName="Syncfusion.UI.Xaml.Charts.CategoryAxis">
      <RootProperty Name="ShowGridLines" />
      <RootProperty Name="Interval" />
      <RootProperty Name="Header" />
      <RootProperty Name="Visibility" />
      <RootProperty Name="Foreground" />
      <RootProperty Name="TickLineSize" />
      <RootProperty Name="MajorGridLineStyle" />
      <RootProperty Name="AxisLineStyle" />
      <RootProperty Name="MajorTickLineStyle" />
      <RootProperty Name="LabelFormat" />
      <RootProperty Name="EdgeLabelsDrawingMode" />
      <RootProperty Name="IsInversed" />
      <RootProperty Name="LabelPlacement" />
      <RootProperty Name="ShowTrackBallInfo" />
      <RootProperty Name="LabelTemplate" />
      <RootProperty Name="PlotOffset" />
      <RootProperty Name="LabelRotationAngle" />
      <RootProperty Name="ZoomFactor" />
      <RootProperty Name="FontSize" />
      <RootProperty Name="HeaderTemplate" />
      <RootProperty Name="AxisLineOffset" />
      <RootProperty Name="ZoomPosition" />
      <RootProperty Name="LabelBorderWidth" />
      <RootProperty Name="ShowLabelBorder" />
      <RootProperty Name="MultiLevelLabels" />
      <RootProperty Name="EnableScrollBar" />
      <RootProperty Name="DeferredScrolling" />
      <RootProperty Name="PositionPath" />
      <RootProperty Name="ContentPath" />
      <RootProperty Name="LabelsSource" />
      <RootProperty Name="StripLines" />
      <RootProperty Name="OpposedPosition" />
      <RootProperty Name="FontFamily" />
    </RootType>
    <RootType FullName="Syncfusion.UI.Xaml.Charts.NumericalAxis">
      <RootProperty Name="ShowGridLines" />
      <RootProperty Name="Header" />
      <RootProperty Name="Visibility" />
      <RootProperty Name="Foreground" />
      <RootProperty Name="TickLineSize" />
      <RootProperty Name="MajorGridLineStyle" />
      <RootProperty Name="AxisLineStyle" />
      <RootProperty Name="Minimum" />
      <RootProperty Name="Interval" />
      <RootProperty Name="MajorTickLineStyle" />
      <RootProperty Name="Maximum" />
      <RootProperty Name="MinorGridLineStyle" />
      <RootProperty Name="PlotOffset" />
      <RootProperty Name="RangePadding" />
      <RootProperty Name="LabelExtent" />
      <RootProperty Name="LabelTemplate" />
      <RootProperty Name="HeaderTemplate" />
      <RootProperty Name="StripLines" />
      <RootProperty Name="ZoomFactor" />
      <RootProperty Name="FontSize" />
      <RootProperty Name="OpposedPosition" />
      <RootProperty Name="ShowTrackBallInfo" />
      <RootProperty Name="EdgeLabelsDrawingMode" />
      <RootProperty Name="LabelFormat" />
      <RootProperty Name="StartRangeFromZero" />
      <RootProperty Name="ShowLabelBorder" />
      <RootProperty Name="PostfixLabelTemplate" />
      <RootProperty Name="LabelBorderWidth" />
      <RootProperty Name="MultiLevelLabels" />
      <RootProperty Name="EnableScrollBar" />
      <RootProperty Name="DeferredScrolling" />
      <RootProperty Name="AxisScaleBreaks" />
      <RootProperty Name="FontFamily" />
      <RootProperty Name="PrefixLabelTemplate" />
    </RootType>
    <RootType FullName="Syncfusion.UI.Xaml.Charts.FastLineSeries">
      <RootProperty Name="Interior" />
      <RootProperty Name="Stroke" />
      <RootProperty Name="ItemsSource" />
      <RootProperty Name="XBindingPath" />
      <RootProperty Name="YBindingPath" />
      <RootProperty Name="Transitions" />
      <RootProperty Name="Label" />
      <RootProperty Name="Trendlines" />
      <RootProperty Name="StrokeThickness" />
      <RootProperty Name="IsTransposed" />
      <RootProperty Name="YAxis" />
      <RootProperty Name="StrokeLineJoin" />
    </RootType>
    <RootType FullName="Syncfusion.SampleBrowser.UWP.SfChart.RangeNavigator_Chart">
      <RootProperty Name="Margin" />
      <RootProperty Name="HorizontalAlignment" />
      <RootProperty Name="Height" />
      <RootEvent Name="PointerEntered" />
      <RootEvent Name="PointerReleased" />
    </RootType>
    <RootType FullName="Syncfusion.UI.Xaml.Charts.ChartSelectionBehavior">
      <RootProperty Name="SelectionCursor" />
      <RootProperty Name="EnableSeriesSelection" />
    </RootType>
    <RootType FullName="Syncfusion.UI.Xaml.Charts.ColumnSeries">
      <RootProperty Name="ItemsSource" />
      <RootProperty Name="SegmentSelectionBrush" />
      <RootProperty Name="XBindingPath" />
      <RootProperty Name="YBindingPath" />
      <RootProperty Name="Interior" />
      <RootProperty Name="Name" />
      <RootProperty Name="Foreground" />
      <RootProperty Name="Label" />
      <RootProperty Name="CustomTemplate" />
      <RootProperty Name="VisibilityOnLegend" />
      <RootProperty Name="Palette" />
      <RootProperty Name="ColorModel" />
      <RootProperty Name="EnableAnimation" />
      <RootProperty Name="ShowTooltip" />
      <RootProperty Name="AdornmentsInfo" />
      <RootProperty Name="ShowEmptyPoints" />
      <RootProperty Name="SeriesSelectionBrush" />
      <RootProperty Name="SegmentSpacing" />
      <RootProperty Name="DragTooltipTemplate" />
      <RootProperty Name="EnableSegmentDragging" />
      <RootProperty Name="YAxis" />
      <RootEvent Name="SegmentEnter" />
      <RootEvent Name="DragStart" />
      <RootEvent Name="DragDelta" />
    </RootType>
    <RootType FullName="Syncfusion.SampleBrowser.UWP.SfChart.DataChart">
      <RootProperty Name="Height" />
      <RootProperty Name="Margin" />
      <RootProperty Name="HorizontalAlignment" />
    </RootType>
    <RootType FullName="Windows.UI.Xaml.Controls.Page">
      <RootProperty Name="RequestedTheme" />
      <RootProperty Name="Resources" />
      <RootProperty Name="Content" />
    </RootType>
    <RootType FullName="Syncfusion.SampleBrowser.UWP.SfChart.ViewModelz" />
    <RootType FullName="Windows.UI.Xaml.Controls.RowDefinition">
      <RootProperty Name="Height" />
    </RootType>
    <RootType FullName="Syncfusion.SampleBrowser.UWP.SfChart.SalesAnalysisDemo" />
    <RootType FullName="Syncfusion.UI.Xaml.Gauges.SfCircularGauge">
      <RootProperty Name="Margin" />
      <RootProperty Name="Height" />
      <RootProperty Name="Width" />
      <RootProperty Name="Scales" />
    </RootType>
    <RootType FullName="Syncfusion.UI.Xaml.Gauges.CircularScale">
      <RootProperty Name="TickPosition" />
      <RootProperty Name="RangePosition" />
      <RootProperty Name="RimStroke" />
      <RootProperty Name="TickStrokeThickness" />
      <RootProperty Name="RimStrokeThickness" />
      <RootProperty Name="ShowRim" />
      <RootProperty Name="TickStroke" />
      <RootProperty Name="SmallTickStroke" />
      <RootProperty Name="LabelStroke" />
      <RootProperty Name="FontSize" />
      <RootProperty Name="FontWeight" />
      <RootProperty Name="Interval" />
      <RootProperty Name="MinorTicksPerInterval" />
      <RootProperty Name="TickLength" />
      <RootProperty Name="StartAngle" />
      <RootProperty Name="SweepAngle" />
      <RootProperty Name="StartValue" />
      <RootProperty Name="EndValue" />
      <RootProperty Name="Ranges" />
      <RootProperty Name="Pointers" />
    </RootType>
    <RootType FullName="Syncfusion.UI.Xaml.Gauges.CircularRange">
      <RootProperty Name="StartValue" />
      <RootProperty Name="EndValue" />
      <RootProperty Name="StrokeThickness" />
      <RootProperty Name="Stroke" />
    </RootType>
    <RootType FullName="Syncfusion.UI.Xaml.Gauges.CircularPointer">
      <RootProperty Name="PointerCapStroke" />
      <RootProperty Name="Value" />
      <RootProperty Name="NeedlePointerStrokeThickness" />
      <RootProperty Name="NeedlePointerStroke" />
      <RootProperty Name="NeedleLengthFactor" />
      <RootProperty Name="PointerCapDiameter" />
    </RootType>
    <RootType FullName="Syncfusion.SampleBrowser.UWP.SfChart.Gauge">
      <RootProperty Name="Margin" />
    </RootType>
    <RootType FullName="Syncfusion.SampleBrowser.UWP.SfChart.SalesHub" />
    <RootType FullName="Windows.UI.Xaml.Controls.ListBox">
      <RootProperty Name="Name" />
      <RootProperty Name="ItemsSource" />
      <RootProperty Name="Background" />
      <RootProperty Name="ItemTemplate" />
      <RootProperty Name="Margin" />
      <RootProperty Name="ItemsPanel" />
      <RootEvent Name="SelectionChanged" />
    </RootType>
    <RootType FullName="Syncfusion.SampleBrowser.UWP.SfChart.AddIndicatorOption" />
    <RootType FullName="Syncfusion.SampleBrowser.UWP.SfChart.DateFormatConverter" />
    <RootType FullName="Syncfusion.SampleBrowser.UWP.SfChart.ConcatConverter" />
    <RootType FullName="Syncfusion.SampleBrowser.UWP.SfChart.ValueConverter" />
    <RootType FullName="Syncfusion.SampleBrowser.UWP.SfChart.TimeStampConverter" />
    <RootType FullName="Windows.UI.Xaml.Controls.ItemsControl">
      <RootProperty Name="ItemsPanel" />
      <RootProperty Name="ItemTemplate" />
      <RootProperty Name="FontSize" />
      <RootProperty Name="ItemsSource" />
    </RootType>
    <RootType FullName="Syncfusion.SampleBrowser.UWP.SfChart.HeaderConverter" />
    <RootType FullName="Syncfusion.SampleBrowser.UWP.SfChart.NameConverter" />
    <RootType FullName="Windows.UI.Xaml.Controls.ItemsPanelTemplate">
      <RootProperty Name="Template" />
    </RootType>
    <RootType FullName="Syncfusion.SampleBrowser.UWP.SfChart.CustomCrossHairbehavior">
      <RootProperty Name="SummaryItemsStyle" />
      <RootProperty Name="HorizontalLineStyle" />
      <RootProperty Name="VerticalLineStyle" />
    </RootType>
    <RootType FullName="Syncfusion.UI.Xaml.Charts.ChartRowDefinition">
      <RootProperty Name="Height" />
      <RootProperty Name="BorderStroke" />
      <RootProperty Name="BorderThickness" />
      <RootProperty Name="Unit" />
    </RootType>
    <RootType FullName="Syncfusion.UI.Xaml.Charts.Watermark">
      <RootProperty Name="HorizontalAlignment" />
      <RootProperty Name="VerticalAlignment" />
      <RootProperty Name="Margin" />
      <RootProperty Name="Content" />
    </RootType>
    <RootType FullName="Syncfusion.UI.Xaml.Charts.DateTimeCategoryAxis">
      <RootProperty Name="Foreground" />
      <RootProperty Name="Interval" />
      <RootProperty Name="LabelFormat" />
      <RootProperty Name="AxisLineStyle" />
      <RootProperty Name="MinorGridLineStyle" />
      <RootProperty Name="PlotOffset" />
      <RootProperty Name="Visibility" />
      <RootProperty Name="EdgeLabelsDrawingMode" />
      <RootProperty Name="IntervalType" />
      <RootProperty Name="MajorGridLineStyle" />
      <RootProperty Name="MajorTickLineStyle" />
      <RootProperty Name="ZoomFactor" />
      <RootProperty Name="ZoomPosition" />
    </RootType>
    <RootType FullName="Syncfusion.UI.Xaml.Charts.HiLoOpenCloseSeries">
      <RootProperty Name="Name" />
      <RootProperty Name="Close" />
      <RootProperty Name="High" />
      <RootProperty Name="Interior" />
      <RootProperty Name="ItemsSource" />
      <RootProperty Name="Label" />
      <RootProperty Name="Low" />
      <RootProperty Name="Open" />
      <RootProperty Name="XBindingPath" />
      <RootProperty Name="YAxis" />
    </RootType>
    <RootType FullName="Syncfusion.UI.Xaml.Charts.ChartSeriesBase">
      <RootMethod Name="GetSpacing" />
      <RootMethod Name="SetSpacing" />
    </RootType>
    <RootType FullName="Syncfusion.UI.Xaml.Charts.ChartBase">
      <RootMethod Name="GetRow" />
      <RootMethod Name="SetRow" />
      <RootMethod Name="GetColumn" />
      <RootMethod Name="SetColumn" />
      <RootMethod Name="GetColumnSpan" />
      <RootMethod Name="SetColumnSpan" />
      <RootMethod Name="GetRowSpan" />
      <RootMethod Name="SetRowSpan" />
    </RootType>
    <RootType FullName="Windows.UI.Xaml.Controls.AppBarButton">
      <RootProperty Name="HorizontalAlignment" />
      <RootProperty Name="BorderThickness" />
      <RootProperty Name="Icon" />
      <RootProperty Name="Margin" />
      <RootEvent Name="Click" />
    </RootType>
    <RootType FullName="Syncfusion.SampleBrowser.UWP.SfChart.Chart" />
    <RootType FullName="Syncfusion.SampleBrowser.UWP.SfChart.StockViewModels" />
    <RootType FullName="Syncfusion.SampleBrowser.UWP.SfChart.FillConverter" />
    <RootType FullName="Syncfusion.SampleBrowser.UWP.SfChart.RotateConverter" />
    <RootType FullName="Syncfusion.UI.Xaml.Controls.Notification.SfHubTile">
      <RootProperty Name="HorizontalAlignment" />
      <RootProperty Name="Background" />
      <RootProperty Name="AccentBrush" />
      <RootProperty Name="Width" />
      <RootProperty Name="BorderThickness" />
      <RootProperty Name="Title" />
    </RootType>
    <RootType FullName="Windows.UI.Xaml.Media.TransformGroup">
      <RootProperty Name="Children" />
    </RootType>
    <RootType FullName="Windows.UI.Xaml.Media.RotateTransform">
      <RootProperty Name="Angle" />
    </RootType>
    <RootType FullName="Windows.UI.Xaml.Media.ScaleTransform">
      <RootProperty Name="ScaleX" />
      <RootProperty Name="ScaleY" />
    </RootType>
    <RootType FullName="Syncfusion.SampleBrowser.UWP.SfChart.StockAnalysis" />
    <RootType FullName="Syncfusion.SampleBrowser.UWP.SfChart.DoubleValueConverter" />
    <RootType FullName="Syncfusion.SampleBrowser.UWP.SfChart.ButtonVisiblityConverter" />
    <RootType FullName="Windows.UI.Xaml.Controls.ComboBox">
      <RootProperty Name="Name" />
      <RootProperty Name="Width" />
      <RootProperty Name="HorizontalAlignment" />
      <RootProperty Name="SelectedIndex" />
      <RootProperty Name="Items" />
      <RootProperty Name="VerticalAlignment" />
      <RootProperty Name="Margin" />
      <RootProperty Name="FontSize" />
      <RootProperty Name="Height" />
      <RootProperty Name="ItemsSource" />
      <RootEvent Name="SelectionChanged" />
    </RootType>
    <RootType FullName="Syncfusion.UI.Xaml.Controls.Layout.SfTileViewItem" />
    <RootType FullName="Syncfusion.UI.Xaml.Controls.Layout.SfTileView">
      <RootProperty Name="Background" />
      <RootProperty Name="BorderBrush" />
      <RootProperty Name="ItemHeight" />
      <RootProperty Name="ItemWidth" />
      <RootProperty Name="ItemsSource" />
      <RootProperty Name="MinimizedItemsOrientation" />
      <RootProperty Name="SelectedIndex" />
      <RootProperty Name="MaximizedItemTemplate" />
      <RootProperty Name="ItemTemplate" />
    </RootType>
    <RootType FullName="Syncfusion.SampleBrowser.UWP.SfChart.SelectionChangedConverter">
      <RootProperty Name="Chart" />
    </RootType>
    <RootType FullName="Syncfusion.UI.Xaml.Charts.Interval">
      <RootProperty Name="IntervalType" />
    </RootType>
    <RootType FullName="Syncfusion.SampleBrowser.UWP.SfChart.CustomTemplateConverter" />
    <RootType FullName="Syncfusion.SampleBrowser.UWP.SfChart.ChartTechnicalIndicatorBehavior" />
    <RootType FullName="Common.SampleLayout">
      <RootProperty Name="Sample" />
      <RootProperty Name="Setting" />
    </RootType>
    <RootType FullName="Windows.UI.Xaml.Controls.ContentControl">
      <RootProperty Name="Margin" />
      <RootProperty Name="Content" />
      <RootProperty Name="HorizontalAlignment" />
      <RootProperty Name="Tag" />
      <RootProperty Name="ContentTemplate" />
    </RootType>
    <RootType FullName="Syncfusion.SampleBrowser.UWP.SfChart.DataViewModel" />
    <RootType FullName="Windows.UI.Xaml.Controls.ComboBoxItem">
      <RootProperty Name="Content" />
    </RootType>
    <RootType FullName="Syncfusion.UI.Xaml.Charts.ChartLegend">
      <RootProperty Name="DockPosition" />
      <RootProperty Name="BorderThickness" />
      <RootProperty Name="ItemTemplate" />
      <RootProperty Name="OffsetX" />
      <RootProperty Name="OffsetY" />
      <RootProperty Name="CheckBoxVisibility" />
      <RootProperty Name="Header" />
      <RootProperty Name="Orientation" />
      <RootProperty Name="IconHeight" />
      <RootProperty Name="IconWidth" />
      <RootProperty Name="Margin" />
      <RootProperty Name="FontSize" />
      <RootProperty Name="LegendPosition" />
      <RootProperty Name="ItemMargin" />
      <RootProperty Name="Foreground" />
      <RootProperty Name="FontFamily" />
    </RootType>
    <RootType FullName="Syncfusion.UI.Xaml.Charts.EllipseAnnotation">
      <RootProperty Name="Fill" />
      <RootProperty Name="Opacity" />
      <RootProperty Name="Stroke" />
      <RootProperty Name="FontWeight" />
      <RootProperty Name="CanDrag" />
      <RootProperty Name="CanResize" />
      <RootProperty Name="CoordinateUnit" />
      <RootProperty Name="X1" />
      <RootProperty Name="X2" />
      <RootProperty Name="Y1" />
      <RootProperty Name="Y2" />
      <RootProperty Name="ContentTemplate" />
    </RootType>
    <RootType FullName="Syncfusion.UI.Xaml.Charts.RectangleAnnotation">
      <RootProperty Name="Fill" />
      <RootProperty Name="Opacity" />
      <RootProperty Name="Stroke" />
      <RootProperty Name="CanDrag" />
      <RootProperty Name="CanResize" />
      <RootProperty Name="CoordinateUnit" />
      <RootProperty Name="X1" />
      <RootProperty Name="X2" />
      <RootProperty Name="Y1" />
      <RootProperty Name="Y2" />
      <RootProperty Name="ContentTemplate" />
    </RootType>
    <RootType FullName="Syncfusion.UI.Xaml.Charts.LineAnnotation">
      <RootProperty Name="Stroke" />
      <RootProperty Name="Fill" />
      <RootProperty Name="CanDrag" />
      <RootProperty Name="CanResize" />
      <RootProperty Name="LineCap" />
      <RootProperty Name="CoordinateUnit" />
      <RootProperty Name="X1" />
      <RootProperty Name="X2" />
      <RootProperty Name="Y1" />
      <RootProperty Name="Y2" />
    </RootType>
    <RootType FullName="Syncfusion.UI.Xaml.Charts.TextAnnotation">
      <RootProperty Name="Width" />
      <RootProperty Name="Height" />
      <RootProperty Name="FontWeight" />
      <RootProperty Name="CanDrag" />
      <RootProperty Name="X1" />
      <RootProperty Name="Y1" />
      <RootProperty Name="FontFamily" />
      <RootProperty Name="ContentTemplate" />
      <RootProperty Name="EnableEditing" />
      <RootProperty Name="Text" />
      <RootProperty Name="FontSize" />
      <RootProperty Name="CoordinateUnit" />
    </RootType>
    <RootType FullName="Syncfusion.UI.Xaml.Charts.HorizontalLineAnnotation">
      <RootProperty Name="Stroke" />
      <RootProperty Name="FontWeight" />
      <RootProperty Name="CanDrag" />
      <RootProperty Name="CanResize" />
      <RootProperty Name="CoordinateUnit" />
      <RootProperty Name="ShowAxisLabel" />
      <RootProperty Name="AxisLabelTemplate" />
      <RootProperty Name="Y1" />
      <RootProperty Name="ContentTemplate" />
    </RootType>
    <RootType FullName="Syncfusion.UI.Xaml.Charts.FastScatterBitmapSeries">
      <RootProperty Name="VisibilityOnLegend" />
      <RootProperty Name="Palette" />
      <RootProperty Name="ColorModel" />
      <RootProperty Name="ItemsSource" />
      <RootProperty Name="XBindingPath" />
      <RootProperty Name="YBindingPath" />
      <RootProperty Name="Label" />
      <RootProperty Name="ShowTooltip" />
      <RootProperty Name="ScatterHeight" />
      <RootProperty Name="ScatterWidth" />
    </RootType>
    <RootType FullName="Syncfusion.UI.Xaml.Charts.VerticalLineAnnotation">
      <RootProperty Name="CanDrag" />
      <RootProperty Name="CanResize" />
      <RootProperty Name="CoordinateUnit" />
      <RootProperty Name="X1" />
      <RootProperty Name="ShowAxisLabel" />
      <RootProperty Name="AxisLabelTemplate" />
    </RootType>
    <RootType FullName="Syncfusion.UI.Xaml.Charts.LineSeries">
      <RootProperty Name="EnableAnimation" />
      <RootProperty Name="ItemsSource" />
      <RootProperty Name="Label" />
      <RootProperty Name="XBindingPath" />
      <RootProperty Name="YBindingPath" />
      <RootProperty Name="AdornmentsInfo" />
      <RootProperty Name="ShowTooltip" />
      <RootProperty Name="XAxis" />
      <RootProperty Name="Opacity" />
      <RootProperty Name="Interior" />
      <RootProperty Name="DragTooltipTemplate" />
      <RootProperty Name="EnableSegmentDragging" />
      <RootProperty Name="Palette" />
      <RootProperty Name="ColorModel" />
      <RootProperty Name="StrokeThickness" />
      <RootEvent Name="SegmentEnter" />
      <RootEvent Name="DragStart" />
      <RootEvent Name="DragDelta" />
    </RootType>
    <RootType FullName="Windows.UI.Xaml.Shapes.Ellipse">
      <RootProperty Name="Height" />
      <RootProperty Name="Width" />
      <RootProperty Name="Margin" />
      <RootProperty Name="Stroke" />
      <RootProperty Name="Fill" />
      <RootProperty Name="StrokeThickness" />
      <RootProperty Name="HorizontalAlignment" />
      <RootProperty Name="IsHitTestVisible" />
      <RootProperty Name="VerticalAlignment" />
    </RootType>
    <RootType FullName="Syncfusion.SampleBrowser.UWP.SfChart.AnnotationViewModel" />
    <RootType FullName="Syncfusion.UI.Xaml.Charts.ImageAnnotation">
      <RootProperty Name="X1" />
      <RootProperty Name="Y1" />
      <RootProperty Name="X2" />
      <RootProperty Name="Y2" />
      <RootProperty Name="ShowToolTip" />
      <RootProperty Name="ToolTipTemplate" />
      <RootProperty Name="ToolTipContent" />
      <RootProperty Name="ToolTipPlacement" />
      <RootProperty Name="HorizontalAlignment" />
      <RootProperty Name="ImageSource" />
    </RootType>
    <RootType FullName="Syncfusion.SampleBrowser.UWP.SfChart.AnnotationDemo" />
    <RootType FullName="Microsoft.Xaml.DirectUI.ProxyTypes.ThemeResourceExtension" />
    <RootType FullName="Windows.UI.Xaml.Controls.Hub">
      <RootProperty Name="Sections" />
    </RootType>
    <RootType FullName="Windows.UI.Xaml.Controls.HubSection">
      <RootProperty Name="Header" />
      <RootProperty Name="Width" />
      <RootProperty Name="ContentTemplate" />
      <RootProperty Name="Margin" />
    </RootType>
    <RootType FullName="Syncfusion.SampleBrowser.UWP.SfChart.InteractionViewModel" />
    <RootType FullName="Syncfusion.SampleBrowser.UWP.SfChart.ProductDetails" />
    <RootType FullName="Syncfusion.UI.Xaml.Charts.DateTimeAxis">
      <RootProperty Name="EnableScrollBarResizing" />
      <RootProperty Name="EnableTouchMode" />
      <RootProperty Name="EnableScrollBar" />
      <RootProperty Name="Header" />
      <RootProperty Name="LabelFormat" />
      <RootProperty Name="AutoScrollingDelta" />
      <RootProperty Name="AutoScrollingDeltaType" />
      <RootProperty Name="EdgeLabelsDrawingMode" />
      <RootProperty Name="LabelTemplate" />
      <RootProperty Name="AxisLineStyle" />
      <RootProperty Name="MajorTickLineStyle" />
      <RootProperty Name="ShowGridLines" />
      <RootProperty Name="ShowTrackBallInfo" />
      <RootProperty Name="PlotOffset" />
      <RootProperty Name="Interval" />
      <RootProperty Name="IntervalType" />
      <RootProperty Name="HeaderTemplate" />
      <RootProperty Name="LabelExtent" />
      <RootProperty Name="FontSize" />
    </RootType>
    <RootType FullName="Syncfusion.UI.Xaml.Charts.ChartStripLine">
      <RootProperty Name="Label" />
      <RootProperty Name="LabelTemplate" />
      <RootProperty Name="Width" />
      <RootProperty Name="Start" />
      <RootProperty Name="Background" />
      <RootProperty Name="IsPixelWidth" />
      <RootProperty Name="LabelAngle" />
      <RootProperty Name="LabelHorizontalAlignment" />
      <RootProperty Name="LabelVerticalAlignment" />
      <RootProperty Name="BorderBrush" />
      <RootProperty Name="BorderThickness" />
    </RootType>
    <RootType FullName="Syncfusion.UI.Xaml.Charts.SplineSeries">
      <RootProperty Name="StrokeThickness" />
      <RootProperty Name="ItemsSource" />
      <RootProperty Name="XBindingPath" />
      <RootProperty Name="YBindingPath" />
      <RootProperty Name="Label" />
      <RootProperty Name="AdornmentsInfo" />
      <RootProperty Name="ShowTooltip" />
      <RootProperty Name="LegendIcon" />
      <RootProperty Name="Interior" />
      <RootProperty Name="CustomTemplate" />
      <RootEvent Name="Loaded" />
    </RootType>
    <RootType FullName="Syncfusion.SampleBrowser.UWP.SfChart.AutoScrollingDemo" />
    <RootType FullName="Syncfusion.SampleBrowser.UWP.SfChart.LineChartLabelConverter" />
    <RootType FullName="Windows.UI.Xaml.Documents.Run">
      <RootProperty Name="Text" />
      <RootProperty Name="FontSize" />
    </RootType>
    <RootType FullName="Syncfusion.SampleBrowser.UWP.SfChart.WheatProductionViewModel" />
    <RootType FullName="Syncfusion.UI.Xaml.Charts.SplineRangeAreaSeries">
      <RootProperty Name="VisibilityOnLegend" />
      <RootProperty Name="EnableAnimation" />
      <RootProperty Name="XBindingPath" />
      <RootProperty Name="ShowTooltip" />
      <RootProperty Name="High" />
      <RootProperty Name="Low" />
      <RootProperty Name="ItemsSource" />
      <RootProperty Name="Interior" />
      <RootProperty Name="Stroke" />
      <RootProperty Name="AdornmentsInfo" />
    </RootType>
    <RootType FullName="Syncfusion.SampleBrowser.UWP.SfChart.BoxWhiskerViewModel" />
    <RootType FullName="Syncfusion.UI.Xaml.Charts.BoxAndWhiskerSeries">
      <RootProperty Name="ItemsSource" />
      <RootProperty Name="XBindingPath" />
      <RootProperty Name="YBindingPath" />
      <RootProperty Name="ShowTooltip" />
      <RootProperty Name="ShowMedian" />
      <RootProperty Name="Palette" />
      <RootProperty Name="ColorModel" />
    </RootType>
    <RootType FullName="Syncfusion.SampleBrowser.UWP.SfChart.WaterfallViewModel" />
    <RootType FullName="Syncfusion.UI.Xaml.Charts.WaterfallSeries">
      <RootProperty Name="EnableAnimation" />
      <RootProperty Name="NegativeSegmentBrush" />
      <RootProperty Name="Interior" />
      <RootProperty Name="SummarySegmentBrush" />
      <RootProperty Name="ItemsSource" />
      <RootProperty Name="XBindingPath" />
      <RootProperty Name="SummaryBindingPath" />
      <RootProperty Name="YBindingPath" />
      <RootProperty Name="ShowTooltip" />
      <RootProperty Name="TooltipTemplate" />
      <RootProperty Name="AdornmentsInfo" />
    </RootType>
    <RootType FullName="Syncfusion.SampleBrowser.UWP.SfChart.HistogramViewModel" />
    <RootType FullName="Syncfusion.UI.Xaml.Charts.HistogramSeries">
      <RootProperty Name="Label" />
      <RootProperty Name="HistogramInterval" />
      <RootProperty Name="ShowTooltip" />
      <RootProperty Name="ItemsSource" />
      <RootProperty Name="VisibilityOnLegend" />
      <RootProperty Name="XBindingPath" />
      <RootProperty Name="YBindingPath" />
      <RootProperty Name="Palette" />
      <RootProperty Name="ColorModel" />
      <RootProperty Name="AdornmentsInfo" />
    </RootType>
    <RootType FullName="Syncfusion.SampleBrowser.UWP.SfChart.ScatterViewModel" />
    <RootType FullName="Syncfusion.UI.Xaml.Charts.ScatterSeries">
      <RootProperty Name="EnableAnimation" />
      <RootProperty Name="VisibilityOnLegend" />
      <RootProperty Name="XBindingPath" />
      <RootProperty Name="ShowTooltip" />
      <RootProperty Name="YBindingPath" />
      <RootProperty Name="ItemsSource" />
      <RootProperty Name="ScatterHeight" />
      <RootProperty Name="ScatterWidth" />
      <RootProperty Name="CustomTemplate" />
      <RootProperty Name="AdornmentsInfo" />
      <RootProperty Name="Label" />
      <RootProperty Name="Interior" />
      <RootProperty Name="Stroke" />
      <RootProperty Name="Opacity" />
      <RootProperty Name="DragDirection" />
      <RootProperty Name="EnableSegmentDragging" />
    </RootType>
    <RootType FullName="Syncfusion.SampleBrowser.UWP.SfChart.LineChartViewModel" />
    <RootType FullName="Syncfusion.SampleBrowser.UWP.SfChart.BasicCharts" />
    <RootType FullName="Syncfusion.SampleBrowser.UWP.SfChart.WaterfallViewModelMobile" />
    <RootType FullName="Syncfusion.UI.Xaml.Charts.StepAreaSeries">
      <RootProperty Name="Stroke" />
      <RootProperty Name="Interior" />
      <RootProperty Name="AdornmentsInfo" />
      <RootProperty Name="XBindingPath" />
      <RootProperty Name="Label" />
      <RootProperty Name="ShowTooltip" />
      <RootProperty Name="YBindingPath" />
      <RootProperty Name="ItemsSource" />
    </RootType>
    <RootType FullName="Syncfusion.UI.Xaml.Charts.StepLineSeries">
      <RootProperty Name="XBindingPath" />
      <RootProperty Name="Label" />
      <RootProperty Name="YBindingPath" />
      <RootProperty Name="AdornmentsInfo" />
      <RootProperty Name="ShowTooltip" />
      <RootProperty Name="ItemsSource" />
    </RootType>
    <RootType FullName="Syncfusion.SampleBrowser.UWP.SfChart.FlexibleAxisDemoViewModel" />
    <RootType FullName="Syncfusion.UI.Xaml.Charts.FastColumnBitmapSeries">
      <RootProperty Name="EnableAnimation" />
      <RootProperty Name="ItemsSource" />
      <RootProperty Name="XBindingPath" />
      <RootProperty Name="YBindingPath" />
      <RootProperty Name="Label" />
      <RootProperty Name="ShowTooltip" />
    </RootType>
    <RootType FullName="Syncfusion.UI.Xaml.Charts.FastHiLoOpenCloseBitmapSeries">
      <RootProperty Name="EnableAnimation" />
      <RootProperty Name="ItemsSource" />
      <RootProperty Name="XBindingPath" />
      <RootProperty Name="High" />
      <RootProperty Name="Low" />
      <RootProperty Name="Open" />
      <RootProperty Name="Close" />
      <RootProperty Name="Label" />
      <RootProperty Name="XAxis" />
      <RootProperty Name="YAxis" />
      <RootProperty Name="BullFillColor" />
      <RootProperty Name="BearFillColor" />
      <RootProperty Name="ShowTooltip" />
      <RootProperty Name="TooltipTemplate" />
      <RootProperty Name="VisibilityOnLegend" />
    </RootType>
    <RootType FullName="Syncfusion.SampleBrowser.UWP.SfChart.FlexibleAxisDemo" />
    <RootType FullName="Syncfusion.SampleBrowser.UWP.SfChart.LogarithmicViewModel" />
    <RootType FullName="Syncfusion.UI.Xaml.Charts.LogarithmicAxis">
      <RootProperty Name="Header" />
      <RootProperty Name="SmallTicksPerInterval" />
    </RootType>
    <RootType FullName="Syncfusion.SampleBrowser.UWP.SfChart.LogarithmicAxis" />
    <RootType FullName="Syncfusion.SampleBrowser.UWP.SfChart.LogarithmicAxisDemo" />
    <RootType FullName="Syncfusion.SampleBrowser.UWP.SfChart.PolarChartViewModel" />
    <RootType FullName="Syncfusion.SampleBrowser.UWP.SfChart.CircularLabelConverter" />
    <RootType FullName="Syncfusion.UI.Xaml.Charts.RadarSeries">
      <RootProperty Name="Opacity" />
      <RootProperty Name="ItemsSource" />
      <RootProperty Name="Label" />
      <RootProperty Name="DrawType" />
      <RootProperty Name="IsClosed" />
      <RootProperty Name="XBindingPath" />
      <RootProperty Name="YBindingPath" />
      <RootProperty Name="StrokeThickness" />
      <RootProperty Name="AdornmentsInfo" />
    </RootType>
    <RootType FullName="Syncfusion.UI.Xaml.Charts.PolarSeries">
      <RootProperty Name="Background" />
      <RootProperty Name="ItemsSource" />
      <RootProperty Name="Label" />
      <RootProperty Name="DrawType" />
      <RootProperty Name="IsClosed" />
      <RootProperty Name="XBindingPath" />
      <RootProperty Name="YBindingPath" />
      <RootProperty Name="StrokeThickness" />
      <RootProperty Name="AdornmentsInfo" />
    </RootType>
    <RootType FullName="Syncfusion.SampleBrowser.UWP.SfChart.PolarAndRadarCharts" />
    <RootType FullName="Syncfusion.SampleBrowser.UWP.SfChart.CurrencyData" />
    <RootType FullName="Syncfusion.UI.Xaml.Charts.ChartCrossHairBehavior">
      <RootProperty Name="HorizontalLineStyle" />
      <RootProperty Name="VerticalLineStyle" />
      <RootProperty Name="HorizontalAxisLabelAlignment" />
      <RootProperty Name="VerticalAxisLabelAlignment" />
    </RootType>
    <RootType FullName="Syncfusion.SampleBrowser.UWP.SfChart.CrossHairDemo" />
    <RootType FullName="Syncfusion.SampleBrowser.UWP.SfChart.ColumnPointsConverter" />
    <RootType FullName="Syncfusion.SampleBrowser.UWP.SfChart.ColumnPointsConverter1" />
    <RootType FullName="Syncfusion.SampleBrowser.UWP.SfChart.SplineValueConverter" />
    <RootType FullName="Syncfusion.SampleBrowser.UWP.SfChart.ScatterInteriorConverter" />
    <RootType FullName="Syncfusion.SampleBrowser.UWP.SfChart.ScatterAngleConverter" />
    <RootType FullName="Syncfusion.SampleBrowser.UWP.SfChart.BarTopConverter" />
    <RootType FullName="Syncfusion.SampleBrowser.UWP.SfChart.ScatterAdornmentConverter" />
    <RootType FullName="Syncfusion.SampleBrowser.UWP.SfChart.ScatterAdornmentForegroundConverter" />
    <RootType FullName="Windows.UI.Xaml.Media.LinearGradientBrush">
      <RootProperty Name="EndPoint" />
      <RootProperty Name="StartPoint" />
      <RootProperty Name="GradientStops" />
    </RootType>
    <RootType FullName="Windows.UI.Xaml.Media.GradientStop">
      <RootProperty Name="Color" />
      <RootProperty Name="Offset" />
    </RootType>
    <RootType FullName="Syncfusion.UI.Xaml.Charts.BarSeries">
      <RootProperty Name="XBindingPath" />
      <RootProperty Name="YBindingPath" />
      <RootProperty Name="ItemsSource" />
      <RootProperty Name="CustomTemplate" />
      <RootProperty Name="SegmentSpacing" />
      <RootProperty Name="Label" />
      <RootProperty Name="LegendIcon" />
      <RootProperty Name="EnableAnimation" />
      <RootProperty Name="Palette" />
      <RootProperty Name="ShowTooltip" />
      <RootProperty Name="TooltipTemplate" />
      <RootProperty Name="ColorModel" />
    </RootType>
    <RootType FullName="Syncfusion.SampleBrowser.UWP.SfChart.CustomTemplate" />
    <RootType FullName="Syncfusion.SampleBrowser.UWP.SfChart.SplineChartViewModel" />
    <RootType FullName="Syncfusion.SampleBrowser.UWP.SfChart.ScatterChartViewModel" />
    <RootType FullName="Syncfusion.SampleBrowser.UWP.SfChart.BarChartViewModel" />
    <RootType FullName="Syncfusion.SampleBrowser.UWP.SfChart.EmptypointViewModel" />
    <RootType FullName="Syncfusion.SampleBrowser.UWP.SfChart.EmptyValues" />
    <RootType FullName="Windows.UI.Xaml.Shapes.Polyline">
      <RootProperty Name="Points" />
      <RootProperty Name="Stroke" />
      <RootProperty Name="StrokeThickness" />
      <RootProperty Name="StrokeDashArray" />
    </RootType>
    <RootType FullName="Syncfusion.SampleBrowser.UWP.SfChart.EnergyProductionDataSample" />
    <RootType FullName="Syncfusion.UI.Xaml.Charts.ErrorBarSeries">
      <RootProperty Name="Name" />
      <RootProperty Name="ItemsSource" />
      <RootProperty Name="XBindingPath" />
      <RootProperty Name="YBindingPath" />
      <RootProperty Name="HorizontalErrorPath" />
      <RootProperty Name="VerticalErrorPath" />
      <RootProperty Name="VerticalErrorValue" />
      <RootProperty Name="HorizontalErrorValue" />
      <RootProperty Name="Mode" />
      <RootProperty Name="HorizontalLineStyle" />
      <RootProperty Name="VerticalLineStyle" />
      <RootProperty Name="HorizontalCapLineStyle" />
      <RootProperty Name="VerticalCapLineStyle" />
    </RootType>
    <RootType FullName="Syncfusion.UI.Xaml.Charts.LineStyle">
      <RootProperty Name="Stroke" />
      <RootProperty Name="StrokeThickness" />
    </RootType>
    <RootType FullName="Syncfusion.UI.Xaml.Charts.CapLineStyle">
      <RootProperty Name="Stroke" />
      <RootProperty Name="StrokeThickness" />
      <RootProperty Name="LineWidth" />
    </RootType>
    <RootType FullName="Syncfusion.SampleBrowser.UWP.SfChart.ErrorBars" />
    <RootType FullName="Windows.UI.Xaml.Controls.TextBox">
      <RootProperty Name="Margin" />
      <RootProperty Name="Text" />
      <RootProperty Name="Width" />
      <RootProperty Name="Visibility" />
      <RootProperty Name="FontSize" />
      <RootProperty Name="VerticalAlignment" />
      <RootEvent Name="TextChanged" />
    </RootType>
    <RootType FullName="Syncfusion.SampleBrowser.UWP.SfChart.DecimalFormatConverter" />
    <RootType FullName="Syncfusion.SampleBrowser.UWP.SfChart.ViewModel" />
    <RootType FullName="Syncfusion.SampleBrowser.UWP.SfChart.FastStackingColumnChartViewModel" />
    <RootType FullName="Syncfusion.UI.Xaml.Charts.ChartZoomPanBehavior" />
    <RootType FullName="Syncfusion.UI.Xaml.Charts.FastStackingColumnBitmapSeries">
      <RootProperty Name="ItemsSource" />
      <RootProperty Name="XBindingPath" />
      <RootProperty Name="YBindingPath" />
      <RootProperty Name="ShowTooltip" />
    </RootType>
    <RootType FullName="Syncfusion.UI.Xaml.Charts.FastHiLoBitmapSeries">
      <RootProperty Name="ItemsSource" />
      <RootProperty Name="XBindingPath" />
      <RootProperty Name="High" />
      <RootProperty Name="Low" />
      <RootProperty Name="ShowTooltip" />
      <RootProperty Name="TooltipTemplate" />
    </RootType>
    <RootType FullName="Syncfusion.UI.Xaml.Charts.FastCandleBitmapSeries">
      <RootProperty Name="ItemsSource" />
      <RootProperty Name="XBindingPath" />
      <RootProperty Name="High" />
      <RootProperty Name="Low" />
      <RootProperty Name="Open" />
      <RootProperty Name="Close" />
      <RootProperty Name="BullFillColor" />
      <RootProperty Name="BearFillColor" />
      <RootProperty Name="ShowTooltip" />
      <RootProperty Name="TooltipTemplate" />
    </RootType>
    <RootType FullName="Syncfusion.UI.Xaml.Charts.FastStepLineBitmapSeries">
      <RootProperty Name="ItemsSource" />
      <RootProperty Name="XBindingPath" />
      <RootProperty Name="YBindingPath" />
      <RootProperty Name="ShowTooltip" />
    </RootType>
    <RootType FullName="Syncfusion.UI.Xaml.Charts.ChartTrackBallBehavior">
      <RootProperty Name="ShowLine" />
      <RootProperty Name="UseSeriesPalette" />
    </RootType>
    <RootType FullName="Syncfusion.UI.Xaml.Charts.FastRangeAreaBitmapSeries">
      <RootProperty Name="ItemsSource" />
      <RootProperty Name="XBindingPath" />
      <RootProperty Name="High" />
      <RootProperty Name="Low" />
      <RootProperty Name="TrackBallLabelTemplate" />
    </RootType>
    <RootType FullName="Syncfusion.UI.Xaml.Charts.FastLineBitmapSeries">
      <RootProperty Name="ItemsSource" />
      <RootProperty Name="XBindingPath" />
      <RootProperty Name="YBindingPath" />
      <RootProperty Name="ShowTooltip" />
      <RootProperty Name="EnableAntiAliasing" />
    </RootType>
    <RootType FullName="Syncfusion.UI.Xaml.Charts.FastBarBitmapSeries">
      <RootProperty Name="ItemsSource" />
      <RootProperty Name="XBindingPath" />
      <RootProperty Name="YBindingPath" />
      <RootProperty Name="ShowTooltip" />
      <RootProperty Name="VisibilityOnLegend" />
    </RootType>
    <RootType FullName="Syncfusion.SampleBrowser.UWP.SfChart.FastChartDemo" />
    <RootType FullName="Syncfusion.SampleBrowser.UWP.SfChart.HiLoChartViewModel" />
    <RootType FullName="Syncfusion.UI.Xaml.Charts.HiLoSeries">
      <RootProperty Name="ItemsSource" />
      <RootProperty Name="XBindingPath" />
      <RootProperty Name="High" />
      <RootProperty Name="Low" />
    </RootType>
    <RootType FullName="Syncfusion.UI.Xaml.Charts.CandleSeries">
      <RootProperty Name="ItemsSource" />
      <RootProperty Name="XBindingPath" />
      <RootProperty Name="High" />
      <RootProperty Name="Low" />
      <RootProperty Name="Open" />
      <RootProperty Name="Close" />
      <RootProperty Name="Name" />
      <RootProperty Name="BullFillColor" />
      <RootProperty Name="BearFillColor" />
      <RootProperty Name="ShowTooltip" />
    </RootType>
    <RootType FullName="Syncfusion.SampleBrowser.UWP.SfChart.FinancialCharts" />
    <RootType FullName="Syncfusion.SampleBrowser.UWP.SfChart.PieChartViewModel" />
    <RootType FullName="Syncfusion.SampleBrowser.UWP.SfChart.FunnelAndPyramidChart" />
    <RootType FullName="Syncfusion.SampleBrowser.UWP.SfChart.MultiLevelLabelViewModel" />
    <RootType FullName="Syncfusion.UI.Xaml.Charts.ChartMultiLevelLabel">
      <RootProperty Name="Start" />
      <RootProperty Name="End" />
      <RootProperty Name="FontSize" />
      <RootProperty Name="Text" />
      <RootProperty Name="Level" />
    </RootType>
    <RootType FullName="Syncfusion.SampleBrowser.UWP.SfChart.MultiLevelLabels" />
    <RootType FullName="Windows.UI.Xaml.Controls.CheckBox">
      <RootProperty Name="IsChecked" />
      <RootProperty Name="MinHeight" />
      <RootProperty Name="MinWidth" />
      <RootProperty Name="RenderTransformOrigin" />
      <RootProperty Name="VerticalAlignment" />
      <RootProperty Name="RenderTransform" />
      <RootProperty Name="Margin" />
      <RootEvent Name="Checked" />
      <RootEvent Name="Unchecked" />
    </RootType>
    <RootType FullName="Syncfusion.UI.Xaml.Charts.ChartColumnDefinition">
      <RootProperty Name="Width" />
    </RootType>
    <RootType FullName="Syncfusion.SampleBrowser.UWP.SfChart.ProductDetails5" />
    <RootType FullName="Syncfusion.UI.Xaml.Charts.ChartLegendCollection" />
    <RootType FullName="Syncfusion.SampleBrowser.UWP.SfChart.MultipleLegendsDemo" />
    <RootType FullName="Syncfusion.UI.Xaml.Charts.SplineAreaSeries">
      <RootProperty Name="Opacity" />
      <RootProperty Name="Label" />
      <RootProperty Name="ItemsSource" />
      <RootProperty Name="XBindingPath" />
      <RootProperty Name="YBindingPath" />
      <RootProperty Name="EnableAnimation" />
      <RootProperty Name="Interior" />
      <RootProperty Name="Stroke" />
    </RootType>
    <RootType FullName="Syncfusion.UI.Xaml.Controls.Layout.SfAccordion">
      <RootProperty Name="AccentBrush" />
      <RootProperty Name="SelectionMode" />
      <RootProperty Name="DataContext" />
      <RootProperty Name="HeaderTemplate" />
      <RootProperty Name="Items" />
    </RootType>
    <RootType FullName="Syncfusion.UI.Xaml.Controls.Layout.SfAccordionItem">
      <RootProperty Name="IsSelected" />
      <RootProperty Name="Header" />
      <RootProperty Name="Content" />
    </RootType>
    <RootType FullName="Windows.UI.Xaml.Controls.Slider">
      <RootProperty Name="Name" />
      <RootProperty Name="VerticalAlignment" />
      <RootProperty Name="Margin" />
      <RootProperty Name="Minimum" />
      <RootProperty Name="Maximum" />
      <RootProperty Name="Value" />
      <RootProperty Name="Width" />
      <RootProperty Name="TickPlacement" />
      <RootProperty Name="Height" />
      <RootProperty Name="HorizontalAlignment" />
      <RootEvent Name="ValueChanged" />
    </RootType>
    <RootType FullName="Syncfusion.SampleBrowser.UWP.SfChart.PaletteViewModel" />
    <RootType FullName="Syncfusion.UI.Xaml.Charts.DoughnutSeries">
      <RootProperty Name="ItemsSource" />
      <RootProperty Name="XBindingPath" />
      <RootProperty Name="YBindingPath" />
      <RootProperty Name="Stroke" />
      <RootProperty Name="StrokeThickness" />
      <RootProperty Name="DoughnutCoefficient" />
      <RootProperty Name="DoughnutSize" />
      <RootProperty Name="ExplodeIndex" />
      <RootProperty Name="ExplodeRadius" />
      <RootProperty Name="LegendIcon" />
      <RootProperty Name="Palette" />
      <RootProperty Name="ColorModel" />
      <RootProperty Name="AdornmentsInfo" />
      <RootProperty Name="StartAngle" />
      <RootProperty Name="EndAngle" />
      <RootProperty Name="EnableSmartLabels" />
      <RootProperty Name="LabelPosition" />
      <RootProperty Name="Label" />
      <RootProperty Name="ShowTooltip" />
      <RootMethod Name="GetDoughnutHoleSize" />
      <RootMethod Name="SetDoughnutHoleSize" />
    </RootType>
    <RootType FullName="Syncfusion.SampleBrowser.UWP.SfChart.Palettes" />
    <RootType FullName="Syncfusion.UI.Xaml.Charts.StackingAreaSeries">
      <RootProperty Name="ItemsSource" />
      <RootProperty Name="XBindingPath" />
      <RootProperty Name="YBindingPath" />
      <RootProperty Name="Label" />
      <RootProperty Name="StrokeThickness" />
      <RootProperty Name="Interior" />
      <RootProperty Name="Stroke" />
      <RootProperty Name="EnableAnimation" />
      <RootProperty Name="AdornmentsInfo" />
    </RootType>
    <RootType FullName="Syncfusion.SampleBrowser.UWP.SfChart.Performance" />
    <RootType FullName="Syncfusion.UI.Xaml.Charts.FunnelSeries">
      <RootProperty Name="ItemsSource" />
      <RootProperty Name="XBindingPath" />
      <RootProperty Name="Label" />
      <RootProperty Name="YBindingPath" />
      <RootProperty Name="ShowTooltip" />
      <RootProperty Name="AdornmentsInfo" />
    </RootType>
    <RootType FullName="Syncfusion.UI.Xaml.Charts.PyramidSeries">
      <RootProperty Name="ItemsSource" />
      <RootProperty Name="XBindingPath" />
      <RootProperty Name="Label" />
      <RootProperty Name="YBindingPath" />
      <RootProperty Name="ShowTooltip" />
      <RootProperty Name="AdornmentsInfo" />
    </RootType>
    <RootType FullName="Syncfusion.SampleBrowser.UWP.SfChart.PieChart" />
    <RootType FullName="Syncfusion.SampleBrowser.UWP.SfChart.LabelConverter" />
    <RootType FullName="Syncfusion.SampleBrowser.UWP.SfChart.PopulationLabelConverter1" />
    <RootType FullName="Syncfusion.SampleBrowser.UWP.SfChart.PopulationLabelConverter2" />
    <RootType FullName="Syncfusion.SampleBrowser.UWP.SfChart.PopulationLabelConverter3" />
    <RootType FullName="Syncfusion.SampleBrowser.UWP.SfChart.PercentageFormatConverter" />
    <RootType FullName="Syncfusion.SampleBrowser.UWP.SfChart.ScalebreakViewModel" />
    <RootType FullName="Syncfusion.UI.Xaml.Charts.ChartAxisScaleBreak">
      <RootProperty Name="Start" />
      <RootProperty Name="End" />
      <RootProperty Name="LineType" />
      <RootProperty Name="StrokeThickness" />
      <RootProperty Name="Fill" />
      <RootProperty Name="BreakSpacing" />
      <RootProperty Name="BreakPercent" />
    </RootType>
    <RootType FullName="Syncfusion.SampleBrowser.UWP.SfChart.ScaleBreak" />
    <RootType FullName="Syncfusion.SampleBrowser.UWP.SfChart.SalePredictionViewModel" />
    <RootType FullName="Syncfusion.SampleBrowser.UWP.SfChart.ScatterDataEditing" />
    <RootType FullName="Syncfusion.SampleBrowser.UWP.SfChart.SeriesSelectionChartViewModel" />
    <RootType FullName="Syncfusion.SampleBrowser.UWP.SfChart.SelectionBehavior" />
    <RootType FullName="Syncfusion.SampleBrowser.UWP.SfChart.SeriesSelection" />
    <RootType FullName="Syncfusion.UI.Xaml.Charts.StackingColumn100Series">
      <RootProperty Name="EnableAnimation" />
      <RootProperty Name="LegendIcon" />
      <RootProperty Name="Interior" />
      <RootProperty Name="Label" />
      <RootProperty Name="XBindingPath" />
      <RootProperty Name="YBindingPath" />
      <RootProperty Name="ItemsSource" />
      <RootProperty Name="AdornmentsInfo" />
    </RootType>
    <RootType FullName="Syncfusion.UI.Xaml.Charts.StackingColumnSeries">
      <RootProperty Name="EnableAnimation" />
      <RootProperty Name="LegendIcon" />
      <RootProperty Name="Interior" />
      <RootProperty Name="Label" />
      <RootProperty Name="XBindingPath" />
      <RootProperty Name="YBindingPath" />
      <RootProperty Name="ItemsSource" />
      <RootProperty Name="AdornmentsInfo" />
      <RootProperty Name="GroupingLabel" />
    </RootType>
    <RootType FullName="Syncfusion.UI.Xaml.Charts.StackingArea100Series">
      <RootProperty Name="StrokeThickness" />
      <RootProperty Name="Interior" />
      <RootProperty Name="Stroke" />
      <RootProperty Name="EnableAnimation" />
      <RootProperty Name="Label" />
      <RootProperty Name="XBindingPath" />
      <RootProperty Name="YBindingPath" />
      <RootProperty Name="AdornmentsInfo" />
      <RootProperty Name="ItemsSource" />
    </RootType>
    <RootType FullName="Syncfusion.UI.Xaml.Charts.StackingBar100Series">
      <RootProperty Name="EnableAnimation" />
      <RootProperty Name="Label" />
      <RootProperty Name="ItemsSource" />
      <RootProperty Name="AdornmentsInfo" />
      <RootProperty Name="XBindingPath" />
      <RootProperty Name="YBindingPath" />
    </RootType>
    <RootType FullName="Syncfusion.UI.Xaml.Charts.StackingBarSeries">
      <RootProperty Name="Label" />
      <RootProperty Name="ItemsSource" />
      <RootProperty Name="XBindingPath" />
      <RootProperty Name="YBindingPath" />
      <RootProperty Name="AdornmentsInfo" />
    </RootType>
    <RootType FullName="Syncfusion.SampleBrowser.UWP.SfChart.StackedCharts" />
    <RootType FullName="Syncfusion.UI.Xaml.Charts.StackingLine100Series">
      <RootProperty Name="EnableAnimation" />
      <RootProperty Name="Label" />
      <RootProperty Name="XBindingPath" />
      <RootProperty Name="YBindingPath" />
      <RootProperty Name="ItemsSource" />
      <RootProperty Name="AdornmentsInfo" />
    </RootType>
    <RootType FullName="Syncfusion.UI.Xaml.Charts.StackingLineSeries">
      <RootProperty Name="EnableAnimation" />
      <RootProperty Name="Label" />
      <RootProperty Name="XBindingPath" />
      <RootProperty Name="YBindingPath" />
      <RootProperty Name="ItemsSource" />
      <RootProperty Name="AdornmentsInfo" />
    </RootType>
    <RootType FullName="Syncfusion.SampleBrowser.UWP.SfChart.StackingGroupViewModel" />
    <RootType FullName="Syncfusion.SampleBrowser.UWP.SfChart.StackingGroup" />
    <RootType FullName="Syncfusion.SampleBrowser.UWP.SfChart.StriplineDemoViewModel" />
    <RootType FullName="Syncfusion.SampleBrowser.UWP.SfChart.StriplinesDemo" />
    <RootType FullName="Syncfusion.UI.Xaml.Charts.ExponentialAverageIndicator">
      <RootProperty Name="Name" />
      <RootProperty Name="ItemsSource" />
      <RootProperty Name="XBindingPath" />
      <RootProperty Name="High" />
      <RootProperty Name="Low" />
      <RootProperty Name="Open" />
      <RootProperty Name="Close" />
    </RootType>
    <RootType FullName="Syncfusion.UI.Xaml.Charts.RSITechnicalIndicator">
      <RootProperty Name="ItemsSource" />
      <RootProperty Name="XBindingPath" />
      <RootProperty Name="High" />
      <RootProperty Name="Low" />
      <RootProperty Name="Open" />
      <RootProperty Name="Close" />
      <RootProperty Name="YAxis" />
    </RootType>
    <RootType FullName="Syncfusion.UI.Xaml.Charts.BollingerBandIndicator">
      <RootProperty Name="Name" />
      <RootProperty Name="ItemsSource" />
      <RootProperty Name="SignalLineColor" />
      <RootProperty Name="Volume" />
      <RootProperty Name="XBindingPath" />
      <RootProperty Name="Period" />
      <RootProperty Name="High" />
      <RootProperty Name="Low" />
      <RootProperty Name="Open" />
      <RootProperty Name="Close" />
      <RootProperty Name="YAxis" />
    </RootType>
    <RootType FullName="Syncfusion.SampleBrowser.UWP.SfChart.TechnicalIndicator" />
    <RootType FullName="Syncfusion.SampleBrowser.UWP.SfChart.ToolTipDemo" />
    <RootType FullName="Syncfusion.UI.Xaml.Charts.ChartTooltipBehavior">
      <RootProperty Name="Style" />
    </RootType>
    <RootType FullName="Syncfusion.SampleBrowser.UWP.SfChart.TrackConverter" />
    <RootType FullName="Syncfusion.SampleBrowser.UWP.SfChart.CommoditiesPrices" />
    <RootType FullName="Syncfusion.SampleBrowser.UWP.SfChart.TrackBallDemo" />
    <RootType FullName="Syncfusion.SampleBrowser.UWP.SfChart.Collection" />
    <RootType FullName="Syncfusion.UI.Xaml.Charts.Trendline">
      <RootProperty Name="Stroke" />
      <RootProperty Name="Type" />
      <RootProperty Name="PolynomialOrder" />
    </RootType>
    <RootType FullName="Syncfusion.SampleBrowser.UWP.SfChart.TrendLineDemo" />
    <RootType FullName="Syncfusion.SampleBrowser.UWP.SfChart.DataDetails" />
    <RootType FullName="Syncfusion.SampleBrowser.UWP.SfChart.VerticalChartDemo" />
    <RootType FullName="Syncfusion.SampleBrowser.UWP.SfChart.StringFormatConverter" />
    <RootType FullName="Syncfusion.SampleBrowser.UWP.SfChart.SalesAnalysisViewModel" />
    <RootType FullName="Syncfusion.SampleBrowser.UWP.SfChart.VisualDataEditing" />
    <RootType FullName="Syncfusion.SampleBrowser.UWP.SfChart.WaterMarkDemo" />
    <RootType FullName="Syncfusion.SampleBrowser.UWP.SfChart.SneakerDetails" />
    <RootType FullName="Syncfusion.SampleBrowser.UWP.SfChart.StringConverter" />
    <RootType FullName="Syncfusion.SampleBrowser.UWP.SfChart.LoadDetailViewModel" />
    <RootType FullName="Syncfusion.SampleBrowser.UWP.SfChart.ZoomPanBehavior" />
    <RootType FullName="Syncfusion.SampleBrowser.UWP.SfChart.ClimateDataViewModel" />
    <RootType FullName="Syncfusion.SampleBrowser.UWP.SfChart.Export" />
    <RootType FullName="Syncfusion.SampleBrowser.UWP.SfChart.ResourceFactory" />
    <RootType FullName="Windows.UI.Color" />
  </Roots.RootTypes>
</Roots>
